lh_tool/__init__.py
lh_tool/compress_pdf.py
lh_tool/concat_image.py
lh_tool/email.py
lh_tool/excel2latex.py
lh_tool/excel2markdown.py
lh_tool/image2gif.py
lh_tool/image2image.py
lh_tool/image2pdf.py
lh_tool/image2video.py
lh_tool/iterator.py
lh_tool/monitor_gpu.py
lh_tool/pcd2ply.py
lh_tool/pdf2image.py
lh_tool/play_image.py
lh_tool/rename_file.py
lh_tool/rename_postfix.py
lh_tool/startup.py
lh_tool/time_consumption.py
lh_tool/timer.py
lh_tool/video2image.py
lh_tool-1.14.0.dist-info/LICENSE
lh_tool-1.14.0.dist-info/METADATA
lh_tool-1.14.0.dist-info/WHEEL
lh_tool-1.14.0.dist-info/entry_points.txt
lh_tool-1.14.0.dist-info/top_level.txt
lh_tool-1.14.0.dist-info/RECORD
