Metadata-Version: 2.1
Name: lh-tool
Version: 1.14.0
Summary: A tool package
Home-page: https://github.com/lh9171338/lh-tool
Author: lh9171338
Author-email: lihao2015@whu.edu.cn
Project-URL: Bug Tracker, https://github.com/lh9171338/lh-tool/issues
Classifier: Programming Language :: Python :: 3
Classifier: License :: OSI Approved :: MIT License
Classifier: Operating System :: OS Independent
Requires-Python: >=3.6
License-File: LICENSE
Requires-Dist: tqdm
Requires-Dist: argparse
Requires-Dist: psutil
Requires-Dist: aiomultiprocess
Provides-Extra: all
Requires-Dist: cv ; extra == 'all'
Requires-Dist: email ; extra == 'all'
Requires-Dist: pdf ; extra == 'all'
Requires-Dist: excel ; extra == 'all'
Requires-Dist: pcd ; extra == 'all'
Requires-Dist: gpu ; extra == 'all'
Provides-Extra: cv
Requires-Dist: opencv-python ; extra == 'cv'
Requires-Dist: imageio ; extra == 'cv'
Provides-Extra: email
Requires-Dist: PyEmail ; extra == 'email'
Requires-Dist: yacs ; extra == 'email'
Provides-Extra: excel
Requires-Dist: xlrd ; extra == 'excel'
Provides-Extra: gpu
Requires-Dist: GPUtil ; extra == 'gpu'
Requires-Dist: pynvml ; extra == 'gpu'
Provides-Extra: pcd
Requires-Dist: pypcd3 ; extra == 'pcd'
Requires-Dist: open3d ; extra == 'pcd'
Provides-Extra: pdf
Requires-Dist: fitz ; extra == 'pdf'
Requires-Dist: PyMuPDF ; extra == 'pdf'
